[{"quantity":1,"year":1927},{"quantity":2,"year":1929},{"quantity":4,"year":1931},{"quantity":1,"year":1932},{"quantity":1,"year":1942},{"quantity":4,"year":1949},{"quantity":1,"year":1954},{"quantity":1,"year":1955},{"quantity":2,"year":1957},{"quantity":2,"year":1962},{"quantity":1,"year":1964},{"quantity":1,"year":1967},{"quantity":2,"year":1968},{"quantity":1,"year":1972},{"quantity":1,"year":1982},{"quantity":2,"year":1991},{"quantity":1,"year":1999},{"quantity":1,"year":2002},{"quantity":2,"year":2004},{"quantity":1,"year":2010},{"quantity":1,"year":2014}]