{"f":[{"name":"maria_victoria","quantity":1373},{"name":"milagros","quantity":1399},{"name":"candela","quantity":1547},{"name":"maria_belen","quantity":1551},{"name":"sofia","quantity":1891},{"name":"rocio_belen","quantity":1953},{"name":"martina","quantity":2331},{"name":"agustina","quantity":2383},{"name":"camila","quantity":2420},{"name":"valentina","quantity":3851}],"m":[{"name":"rodrigo_alejandro","quantity":1528},{"name":"nicolas","quantity":1578},{"name":"joaquin","quantity":1595},{"name":"francisco","quantity":1649},{"name":"juan_pablo","quantity":1707},{"name":"juan_cruz","quantity":1770},{"name":"santiago","quantity":1807},{"name":"tomas","quantity":2299},{"name":"juan_ignacio","quantity":2487},{"name":"agustin","quantity":2614}]}